django_advance_thumbnail/__init__.py
django_advance_thumbnail/admin.py
django_advance_thumbnail/apps.py
django_advance_thumbnail/fields.py
django_advance_thumbnail/models.py
django_advance_thumbnail/tests.py
django_advance_thumbnail/views.py
django_advance_thumbnail/__pycache__/__init__.cpython-314.pyc
django_advance_thumbnail/__pycache__/apps.cpython-314.pyc
django_advance_thumbnail/__pycache__/fields.cpython-314.pyc
django_advance_thumbnail/__pycache__/models.cpython-314.pyc
django_advance_thumbnail/management/__init__.py
django_advance_thumbnail/management/__pycache__/__init__.cpython-314.pyc
django_advance_thumbnail/management/commands/__init__.py
django_advance_thumbnail/management/commands/generate_thumbnails.py
django_advance_thumbnail/management/commands/regenerate_thumbnails.py
django_advance_thumbnail/migrations/__init__.py
django_advance_thumbnail/migrations/__pycache__/__init__.cpython-314.pyc
django_advance_thumbnail-2.0.0.dist-info/licenses/LICENSE
django_advance_thumbnail-2.0.0.dist-info/METADATA
django_advance_thumbnail-2.0.0.dist-info/WHEEL
django_advance_thumbnail-2.0.0.dist-info/top_level.txt
django_advance_thumbnail-2.0.0.dist-info/RECORD
