Metadata-Version: 2.4
Name: django_advance_thumbnail
Version: 2.0.0
Summary: A Django app that automates thumbnail creation for image fields.
Author-email: Mahadi Hassan <mh@mahadihassan.com>
License-Expression: MIT
Project-URL: Homepage, https://github.com/itsmahadi007/django_advance_thumbnail
Project-URL: Repository, https://github.com/itsmahadi007/django_advance_thumbnail
Project-URL: Issues, https://github.com/itsmahadi007/django_advance_thumbnail/issues
Classifier: Environment :: Web Environment
Classifier: Framework :: Django
Classifier: Framework :: Django :: 3.0
Classifier: Framework :: Django :: 3.1
Classifier: Framework :: Django :: 3.2
Classifier: Framework :: Django :: 4.0
Classifier: Framework :: Django :: 4.1
Classifier: Framework :: Django :: 4.2
Classifier: Framework :: Django :: 5.0
Classifier: Framework :: Django :: 5.1
Classifier: Framework :: Django :: 5.2
Classifier: Intended Audience :: Developers
Classifier: Operating System :: OS Independent
Classifier: Programming Language :: Python :: 3.6
Classifier: Programming Language :: Python :: 3.7
Classifier: Programming Language :: Python :: 3.8
Classifier: Programming Language :: Python :: 3.9
Classifier: Programming Language :: Python :: 3.10
Classifier: Programming Language :: Python :: 3.11
Classifier: Programming Language :: Python :: 3.12
Classifier: Topic :: Internet :: WWW/HTTP
Classifier: Topic :: Internet :: WWW/HTTP :: Dynamic Content
Requires-Python: >=3.6
License-File: LICENSE
Requires-Dist: Django>=3.0
Requires-Dist: Pillow>=8.0.0
Dynamic: license-file
